MANIFEST.in
README.rst
setup.cfg
setup.py
daemonator/__init__.py
daemonator/daemonator.py
daemonator.egg-info/PKG-INFO
daemonator.egg-info/SOURCES.txt
daemonator.egg-info/dependency_links.txt
daemonator.egg-info/pbr.json
daemonator.egg-info/top_level.txt