Metadata-Version: 1.1
Name: daemonator
Version: 0.4.1
Summary: Lightweight and no-nonsense POSIX daemon library for Python (2.x.x/3.x.x)
Home-page: https://github.com/flaviocpontes/daemonator
Author: Flávio Cardoso Pontes
Author-email: <flaviopontes@acerp.org.br>
License: MIT/X11
Download-URL: https://github.com/flaviocpontes/daemonator/tarball/0.4.1
Platform: Linux
